opcalc/__init__.py
opcalc/core.py
opcalc-0.0.1a3.dist-info/LICENSE
opcalc-0.0.1a3.dist-info/METADATA
opcalc-0.0.1a3.dist-info/WHEEL
opcalc-0.0.1a3.dist-info/top_level.txt
opcalc-0.0.1a3.dist-info/RECORD
