Metadata-Version: 2.1
Name: opcalc
Version: 0.0.1a3
Summary: Simple tool for calculate the numerical result from a expression string by python
Home-page: https://github.com/qxdnfsy/python-opcalc
Author: Quix Fan @ZQWEI-Tech
Author-email: qxdnfsy@126.com
License: MIT
Platform: UNKNOWN
Classifier: Programming Language :: Python :: 3
Classifier: License :: OSI Approved :: MIT License
Classifier: Operating System :: OS Independent
